clientapi_barion/__init__.py
clientapi_barion/api_client.py
clientapi_barion/api_response.py
clientapi_barion/barion.py
clientapi_barion/configuration.py
clientapi_barion/exceptions.py
clientapi_barion/py.typed
clientapi_barion/rest.py
clientapi_barion/api/__init__.py
clientapi_barion/api/barion_smart_gateway_api.py
clientapi_barion/api/barion_wallet_api.py
clientapi_barion/models/__init__.py
clientapi_barion/models/account.py
clientapi_barion/models/account_info.py
clientapi_barion/models/accounts_response.py
clientapi_barion/models/accounts_response_with_error_messages.py
clientapi_barion/models/balance.py
clientapi_barion/models/bank_account_details.py
clientapi_barion/models/bank_card.py
clientapi_barion/models/bank_details.py
clientapi_barion/models/beneficiary.py
clientapi_barion/models/billing_address.py
clientapi_barion/models/cancel_authorization_request.py
clientapi_barion/models/cancel_authorization_response.py
clientapi_barion/models/cancel_authorization_response_with_error_messages.py
clientapi_barion/models/capture_payment_request.py
clientapi_barion/models/capture_payment_response.py
clientapi_barion/models/capture_payment_response_with_error_messages.py
clientapi_barion/models/detailed_payment_transaction.py
clientapi_barion/models/detailed_payment_transaction_transaction_type.py
clientapi_barion/models/error.py
clientapi_barion/models/errors.py
clientapi_barion/models/funding_information.py
clientapi_barion/models/get_payment_state_response.py
clientapi_barion/models/get_payment_state_response_with_error_messages.py
clientapi_barion/models/get_user_history_response.py
clientapi_barion/models/get_user_history_response_with_error_messages.py
clientapi_barion/models/gift_card_purchase.py
clientapi_barion/models/item.py
clientapi_barion/models/name_information.py
clientapi_barion/models/payee_transaction.py
clientapi_barion/models/payee_transaction_to_finish.py
clientapi_barion/models/payer_account_information.py
clientapi_barion-0.1.1.dist-info/METADATA
clientapi_barion-0.1.1.dist-info/WHEEL
clientapi_barion-0.1.1.dist-info/top_level.txt
clientapi_barion-0.1.1.dist-info/RECORD
